dexhub/__init__.py
dexhub/data_types.py
dexhub/download.py
dexhub/init.py
dexhub/sas_logging.py
dexhub/upload.py
dexhub/avp/__init__.py
dexhub/avp/grpc_avp_client.py
dexhub/avp/grpc_robot_client.py
dexhub/avp/grpc_robot_server.py
dexhub/avp/grpc_msg/__init__.py
dexhub/avp/grpc_msg/dexterity_pb2.py
dexhub/avp/grpc_msg/dexterity_pb2_grpc.py
dexhub/avp/grpc_msg/handtracking_pb2.py
dexhub/avp/grpc_msg/handtracking_pb2_grpc.py
dexhub/avp/utils/__init__.py
dexhub/avp/utils/grpc_utils.py
dexhub/avp/utils/isaac_utils.py
dexhub/avp/utils/se3_utils.py
dexhub/avp/utils/trn_constants.py
dexhub/utils/__init__.py
dexhub/utils/dataset.py
dexhub/utils/meshcat_viz.py
meshcat/__init__.py
meshcat/animation.py
meshcat/commands.py
meshcat/geometry.py
meshcat/path.py
meshcat/transformations.py
meshcat/visualizer.py
meshcat/servers/__init__.py
meshcat/servers/tree.py
meshcat/servers/zmqserver.py
meshcat/tests/__init__.py
meshcat/tests/dummy_websocket_client.py
meshcat/tests/test_drawing.py
meshcat/tests/test_ports.py
meshcat/tests/test_start_server.py
dexhub_api-0.8.5.dist-info/METADATA
dexhub_api-0.8.5.dist-info/WHEEL
dexhub_api-0.8.5.dist-info/top_level.txt
dexhub_api-0.8.5.dist-info/RECORD
