Metadata-Version: 2.1
Name: dexhub-api
Version: 0.8.5
Requires-Dist: requests
Requires-Dist: numpy>=1.14.0
Requires-Dist: scipy
Requires-Dist: mujoco
Requires-Dist: dm-control
Requires-Dist: ipython>=5
Requires-Dist: u-msgpack-python>=2.4.1
Requires-Dist: tornado>=4.0.0
Requires-Dist: pyzmq>=17.0.0
Requires-Dist: pyngrok>=4.1.6
Requires-Dist: pillow>=7.0.0
Requires-Dist: imageio
Requires-Dist: matplotlib
Requires-Dist: ffmpeg
Requires-Dist: imageio-ffmpeg
